torcherry/__init__.py
torcherry/core.py
torcherry/module.py
torcherry/dataset/__init__.py
torcherry/dataset/dali/__init__.py
torcherry/dataset/dali/preprocess_cifar10.py
torcherry/dataset/dali/preprocess_cifar100.py
torcherry/dataset/dali/preprocess_fashion_mnist.py
torcherry/dataset/dali/preprocess_imagenet.py
torcherry/dataset/dali/preprocess_mnist.py
torcherry/dataset/dali/preprocess_svhn.py
torcherry/dataset/dali/util_cifar10.py
torcherry/dataset/dali/util_cifar100.py
torcherry/dataset/dali/util_fashion_mnist.py
torcherry/dataset/dali/util_mnist.py
torcherry/dataset/dali/util_svhn.py
torcherry/utils/__init__.py
torcherry/utils/checkpoint.py
torcherry/utils/metric.py
torcherry/utils/scheduler.py
torcherry/utils/util.py
torcherry-0.2.0.dist-info/LICENSE
torcherry-0.2.0.dist-info/METADATA
torcherry-0.2.0.dist-info/WHEEL
torcherry-0.2.0.dist-info/top_level.txt
torcherry-0.2.0.dist-info/RECORD
