Metadata-Version: 2.1
Name: torcherry
Version: 0.2.0
Summary: torcherry: a higher framework for pytorch.
Home-page: https://github.com/perryuu/torcherry
Author: Perry
Maintainer: Perry
License: GPLv3
Platform: any
Requires-Dist: torch (>=1.0.0)
